respan_exporter_openai_agents/__init__.py
respan_exporter_openai_agents/respan_openai_agents_exporter.py
respan_exporter_openai_agents/types.py
respan_exporter_openai_agents-1.0.1.dist-info/METADATA
respan_exporter_openai_agents-1.0.1.dist-info/WHEEL
respan_exporter_openai_agents-1.0.1.dist-info/RECORD
