Metadata-Version: 2.1
Name: respan-exporter-openai-agents
Version: 1.0.1
Summary: Exporter for Respan OpenAI Agents SDK
License: Apache 2.0
Author: Respan
Author-email: team@respan.ai
Requires-Python: >3.10,<3.13
Classifier: License :: Other/Proprietary License
Classifier: Programming Language :: Python :: 3
Classifier: Programming Language :: Python :: 3.11
Classifier: Programming Language :: Python :: 3.12
Requires-Dist: openai-agents (>=0.3.1,<0.4.0)
Requires-Dist: respan-sdk (>=1.0.0,<2.0.0)
